setup.py
jseg/__init__.py
jseg/brill_tagger.pkl
jseg/dict.txt
jseg/emoall.txt
jseg/emodet.py
jseg/jieba.py
jseg/test.py
jseg.egg-info/PKG-INFO
jseg.egg-info/SOURCES.txt
jseg.egg-info/dependency_links.txt
jseg.egg-info/requires.txt
jseg.egg-info/top_level.txt
jseg/Emodet/__init__.py
jseg/Emodet/emodet.py
jseg/Emodet/emodet2.py
jseg/prob/emisP.json
jseg/prob/initP.json
jseg/prob/tranP.json