Metadata-Version: 1.0
Name: jseg
Version: 0.0.4
Summary: A modified version of Jieba
Home-page: UNKNOWN
Author: Aji Liu
Author-email: amigcamel@gmail.com
License: UNKNOWN
Platform: UNKNOWN
